bmi_simple_calc/calc.py
bmi_simple_calc-0.0.0.2.dist-info/METADATA
bmi_simple_calc-0.0.0.2.dist-info/WHEEL
bmi_simple_calc-0.0.0.2.dist-info/top_level.txt
bmi_simple_calc-0.0.0.2.dist-info/RECORD
