Metadata-Version: 2.1
Name: bmi-simple-calc
Version: 0.0.0.2
Summary: calculation human bmi value
Home-page: https://news.naver.com
Author: HanByulLee
Author-email: stargen@gmail.com
License: MIT
Platform: UNKNOWN
Requires-Python: >=3
